README.rst
decouple.py
setup.py
django_decouple.egg-info/PKG-INFO
django_decouple.egg-info/SOURCES.txt
django_decouple.egg-info/dependency_links.txt
django_decouple.egg-info/not-zip-safe
django_decouple.egg-info/top_level.txt