Metadata-Version: 1.0
Name: django-decouple
Version: 1.0
Summary: Strict separation of settings from code.
Home-page: http://github.com/henriquebastos/django-decouple/
Author: Henrique Bastos
Author-email: henrique@bastos.net
License: MIT
Platform: any
Classifier: Development Status :: 5 - Production/Stable
Classifier: Framework :: Django
Classifier: Intended Audience :: Developers
Classifier: License :: OSI Approved :: MIT License
Classifier: Natural Language :: English
Classifier: Operating System :: OS Independent
Classifier: Programming Language :: Python
Classifier: Topic :: Software Development :: Libraries
